{"categoryGeneratedIndex":{"title":"Util - Reportes","description":"Funcionalidades para manejar report services","slug":"/category/util---reportes","permalink":"/IDAE.Docs/docs/category/util---reportes","sidebar":"tutorialSidebar","navigation":{"previous":{"title":"Configuración de Envío JSON en Integraciones","permalink":"/IDAE.Docs/docs/sammnew/Integration/configuration-Support-for-JSON-STRING-and-native-JSON"},"next":{"title":"Configuración de Búsqueda en Campos Lista","permalink":"/IDAE.Docs/docs/util-reportes/search-settings"}}}}